LICENSE.txt
README.rst
setup.py
tpw/__init__.py
tpw/core.py
tpw/response.py
tpw_framework.egg-info/PKG-INFO
tpw_framework.egg-info/SOURCES.txt
tpw_framework.egg-info/dependency_links.txt
tpw_framework.egg-info/top_level.txt