Metadata-Version: 2.1
Name: tpw-framework
Version: 1.0.0
Summary: Lightweight python web framework
Home-page: https://github.com/AdminTima/tpw_framework
Author: Tim Admin
Author-email: h.timofey.mail@gmail.com
License: Copyright (c) [2022] [TimAdmin]  Permission is hereby granted, free of charge, to any person obtaining a copy of this software and associated documentation files (the "Software"), to deal in the Software without restriction, including without limitation the rights to use, copy, modify, merge, publish, distribute, sublicense, and/or sell copies of the Software, and to permit persons to whom the Software is furnished to do so, subject to the following conditions:  The above copyright noti
Platform: UNKNOWN
License-File: LICENSE.txt
